jaxeffort/__init__.py
jaxeffort/jaxeffort.py
jaxeffort-0.2.4.dist-info/LICENSE
jaxeffort-0.2.4.dist-info/METADATA
jaxeffort-0.2.4.dist-info/WHEEL
jaxeffort-0.2.4.dist-info/RECORD
