Metadata-Version: 2.1
Name: jaxeffort
Version: 0.2.4
Summary: JAX-based emulator for galaxy power spectra with bias modeling
Author: marcobonici
Author-email: bonici.marco@gmail.com
Requires-Python: >=3.10,<4.0
Classifier: Programming Language :: Python :: 3
Classifier: Programming Language :: Python :: 3.10
Classifier: Programming Language :: Python :: 3.11
Classifier: Programming Language :: Python :: 3.12
Requires-Dist: fetch-artifacts (>=0.1.0,<0.2.0)
Requires-Dist: flax (>=0.10.0,<0.11.0)
Requires-Dist: jax (>=0.4.30)
Requires-Dist: jaxace (>=0.4.0,<0.5.0)
Requires-Dist: numpy (>=2.2.6,<3.0.0)
